{
  "resourceType": "Questionnaire",
  "item": [
    {
      "linkId": "1",
      "type": "group",
      "extension": [
        {
          "url": "http://hl7.org/fhir/StructureDefinition/questionnaire-itemControl",
          "valueCodeableConcept": {
            "coding": [
              {
                "system": "http://hl7.org/fhir/questionnaire-item-control",
                "code": "page",
                "display": "Page"
              }
            ],
            "text": "Page"
          }
        }
      ],
      "item": [
        {
          "linkId": "1.1",
          "type": "display",
          "text": "Personal information",
          "prefix": "1."
        },
        {
          "linkId": "1.2",
          "type": "string",
          "item": [
            {
              "linkId": "1.2.1",
              "text": "First Name",
              "type": "display",
              "extension": [
                {
                  "url": "http://hl7.org/fhir/StructureDefinition/questionnaire-itemControl",
                  "valueCodeableConcept": {
                    "coding": [
                      {
                        "system": "http://hl7.org/fhir/questionnaire-item-control",
                        "code": "flyover",
                        "display": "Fly-over"
                      }
                    ],
                    "text": "Flyover"
                  }
                }
              ]
            }
          ]
        },
        {
          "linkId": "1.3",
          "type": "string",
          "item": [
            {
              "linkId": "1.3.1",
              "text": "Family Name",
              "type": "display",
              "extension": [
                {
                  "url": "http://hl7.org/fhir/StructureDefinition/questionnaire-itemControl",
                  "valueCodeableConcept": {
                    "coding": [
                      {
                        "system": "http://hl7.org/fhir/questionnaire-item-control",
                        "code": "flyover",
                        "display": "Fly-over"
                      }
                    ],
                    "text": "Flyover"
                  }
                }
              ]
            }
          ]
        },
        {
          "linkId": "1.4",
          "type": "integer",
          "item": [
            {
              "linkId": "1.4.1",
              "text": "ID number",
              "type": "display",
              "extension": [
                {
                  "url": "http://hl7.org/fhir/StructureDefinition/questionnaire-itemControl",
                  "valueCodeableConcept": {
                    "coding": [
                      {
                        "system": "http://hl7.org/fhir/questionnaire-item-control",
                        "code": "flyover",
                        "display": "Fly-over"
                      }
                    ],
                    "text": "Flyover"
                  }
                }
              ]
            }
          ]
        },
        {
          "linkId": "1.5",
          "type": "integer",
          "item": [
            {
              "linkId": "1.5.1",
              "text": "Mobile number",
              "type": "display",
              "extension": [
                {
                  "url": "http://hl7.org/fhir/StructureDefinition/questionnaire-itemControl",
                  "valueCodeableConcept": {
                    "coding": [
                      {
                        "system": "http://hl7.org/fhir/questionnaire-item-control",
                        "code": "flyover",
                        "display": "Fly-over"
                      }
                    ],
                    "text": "Flyover"
                  }
                }
              ]
            }
          ]
        },
        {
          "linkId": "1.6",
          "type": "choice",
          "repeats": true,
          "extension": [
            {
              "url": "http://hl7.org/fhir/StructureDefinition/questionnaire-itemControl",
              "valueCodeableConcept": {
                "coding": [
                  {
                    "system": "http://hl7.org/fhir/questionnaire-item-control",
                    "code": "check-box",
                    "display": "Checkbox"
                  }
                ],
                "text": "Checkbox"
              }
            }
          ],
          "answerOption": [
            {
              "valueCoding": {
                "code": "code",
                "display": "Receive SMS reminders"
              }
            }
          ]
        }
      ]
    },
    {
      "linkId": "2",
      "type": "group",
      "extension": [
        {
          "url": "http://hl7.org/fhir/StructureDefinition/questionnaire-itemControl",
          "valueCodeableConcept": {
            "coding": [
              {
                "system": "http://hl7.org/fhir/questionnaire-item-control",
                "code": "page",
                "display": "Page"
              }
            ],
            "text": "Page"
          }
        }
      ],
      "item": [
        {
          "linkId": "2.1",
          "type": "date",
          "text": "Date of birth",
          "prefix": "2."
        },
        {
          "linkId": "2.2",
          "type": "choice",
          "repeats": true,
          "extension": [
            {
              "url": "http://hl7.org/fhir/StructureDefinition/questionnaire-itemControl",
              "valueCodeableConcept": {
                "coding": [
                  {
                    "system": "http://hl7.org/fhir/questionnaire-item-control",
                    "code": "check-box",
                    "display": "Checkbox"
                  }
                ],
                "text": "Checkbox"
              }
            }
          ],
          "answerOption": [
            {
              "valueCoding": {
                "code": "code1",
                "display": "Unknown birthday"
              }
            }
          ]
        }
      ]
    },
    {
      "linkId": "3",
      "type": "group",
      "extension": [
        {
          "url": "http://hl7.org/fhir/StructureDefinition/questionnaire-itemControl",
          "valueCodeableConcept": {
            "coding": [
              {
                "system": "http://hl7.org/fhir/questionnaire-item-control",
                "code": "page",
                "display": "Page"
              }
            ],
            "text": "Page"
          }
        }
      ],
      "item": [
        {
          "linkId": "3.1",
          "type": "display",
          "text": "Address",
          "prefix":"3."
        },
        {
          "linkId": "3.2",
          "type": "string",
          "item": [
            {
              "linkId": "10.1",
              "text": "House number and street",
              "type": "display",
              "extension": [
                {
                  "url": "http://hl7.org/fhir/StructureDefinition/questionnaire-itemControl",
                  "valueCodeableConcept": {
                    "coding": [
                      {
                        "system": "http://hl7.org/fhir/questionnaire-item-control",
                        "code": "flyover",
                        "display": "Fly-over"
                      }
                    ],
                    "text": "Flyover"
                  }
                }
              ]
            }
          ]
        },
        {
          "linkId": "3.3",
          "type": "string",
          "item": [
            {
              "linkId": "11.1",
              "text": "Apartment, unit",
              "type": "display",
              "extension": [
                {
                  "url": "http://hl7.org/fhir/StructureDefinition/questionnaire-itemControl",
                  "valueCodeableConcept": {
                    "coding": [
                      {
                        "system": "http://hl7.org/fhir/questionnaire-item-control",
                        "code": "flyover",
                        "display": "Fly-over"
                      }
                    ],
                    "text": "Flyover"
                  }
                }
              ]
            }
          ]
        },
        {
          "linkId": "3.4",
          "type": "string",
          "item": [
            {
              "linkId": "12.1",
              "text": "City, town or village",
              "type": "display",
              "extension": [
                {
                  "url": "http://hl7.org/fhir/StructureDefinition/questionnaire-itemControl",
                  "valueCodeableConcept": {
                    "coding": [
                      {
                        "system": "http://hl7.org/fhir/questionnaire-item-control",
                        "code": "flyover",
                        "display": "Fly-over"
                      }
                    ],
                    "text": "Flyover"
                  }
                }
              ]
            }
          ]
        },
        {
          "linkId": "3.5",
          "type": "string",
          "item": [
            {
              "linkId": "13.1",
              "text": "County",
              "type": "display",
              "extension": [
                {
                  "url": "http://hl7.org/fhir/StructureDefinition/questionnaire-itemControl",
                  "valueCodeableConcept": {
                    "coding": [
                      {
                        "system": "http://hl7.org/fhir/questionnaire-item-control",
                        "code": "flyover",
                        "display": "Fly-over"
                      }
                    ],
                    "text": "Flyover"
                  }
                }
              ]
            }
          ]
        },
        {
          "linkId": "3.6",
          "type": "string",
          "item": [
            {
              "linkId": "14.1",
              "text": "Postal Code",
              "type": "display",
              "extension": [
                {
                  "url": "http://hl7.org/fhir/StructureDefinition/questionnaire-itemControl",
                  "valueCodeableConcept": {
                    "coding": [
                      {
                        "system": "http://hl7.org/fhir/questionnaire-item-control",
                        "code": "flyover",
                        "display": "Fly-over"
                      }
                    ],
                    "text": "Flyover"
                  }
                }
              ]
            }
          ]
        }
      ]
    },
    {
      "linkId": "4",
      "type": "group",
      "extension": [
        {
          "url": "http://hl7.org/fhir/StructureDefinition/questionnaire-itemControl",
          "valueCodeableConcept": {
            "coding": [
              {
                "system": "http://hl7.org/fhir/questionnaire-item-control",
                "code": "page",
                "display": "Page"
              }
            ],
            "text": "Page"
          }
        }
      ],
      "item": [
        {
          "linkId": "4.1",
          "type": "display",
          "text": "Alternative contact person",
          "prefix":"4.",
          "item": [
            {
              "linkId": "15.1",
              "text": "The alternative contact would be used in the case of an emergency situation and could be next of kin (e.g. partner, mother, sibling.)",
              "type": "display"
            }
          ]
        },
        {
          "linkId": "4.2",
          "type": "string",
          "item": [
            {
              "linkId": "16.1",
              "text": "Name",
              "type": "display",
              "extension": [
                {
                  "url": "http://hl7.org/fhir/StructureDefinition/questionnaire-itemControl",
                  "valueCodeableConcept": {
                    "coding": [
                      {
                        "system": "http://hl7.org/fhir/questionnaire-item-control",
                        "code": "flyover",
                        "display": "Fly-over"
                      }
                    ],
                    "text": "Flyover"
                  }
                }
              ]
            }
          ]
        },
        {
          "linkId": "4.3",
          "type": "choice",
          "extension": [
            {
              "url": "http://hl7.org/fhir/StructureDefinition/questionnaire-itemControl",
              "valueCodeableConcept": {
                "coding": [
                  {
                    "system": "http://hl7.org/fhir/questionnaire-item-control",
                    "code": "drop-down",
                    "display": "Drop down"
                  }
                ],
                "text": "Drop down"
              }
            }
          ],
          "item": [
            {
              "linkId": "17.1",
              "text": "Relationship",
              "type": "display",
              "extension": [
                {
                  "url": "http://hl7.org/fhir/StructureDefinition/questionnaire-itemControl",
                  "valueCodeableConcept": {
                    "coding": [
                      {
                        "system": "http://hl7.org/fhir/questionnaire-item-control",
                        "code": "flyover",
                        "display": "Fly-over"
                      }
                    ],
                    "text": "Flyover"
                  }
                }
              ]
            }
          ],
          "answerOption": [
            {
              "valueCoding": {
                "code": "child",
                "display": "Child"
              }
            },
            {
              "valueCoding": {
                "code": "father",
                "display": "Father"
              }
            },
            {
              "valueCoding": {
                "code": "mother",
                "display": "Mother"
              }
            },
            {
              "valueCoding": {
                "code": "sibling",
                "display": "Sibling"
              }
            },
            {
              "valueCoding": {
                "code": "other",
                "display": "Other"
              }
            }
          ]
        },
        {
          "linkId": "4.4",
          "type": "string",
          "item": [
            {
              "linkId": "18.1",
              "text": "Phone number",
              "type": "display",
              "extension": [
                {
                  "url": "http://hl7.org/fhir/StructureDefinition/questionnaire-itemControl",
                  "valueCodeableConcept": {
                    "coding": [
                      {
                        "system": "http://hl7.org/fhir/questionnaire-item-control",
                        "code": "flyover",
                        "display": "Fly-over"
                      }
                    ],
                    "text": "Flyover"
                  }
                }
              ]
            }
          ]
        }
      ]
    },
    {
      "linkId": "5",
      "type": "group",
      "extension": [
        {
          "url": "http://hl7.org/fhir/StructureDefinition/questionnaire-itemControl",
          "valueCodeableConcept": {
            "coding": [
              {
                "system": "http://hl7.org/fhir/questionnaire-item-control",
                "code": "page",
                "display": "Page"
              }
            ],
            "text": "Page"
          }
        }
      ],
      "item": [
        {
          "linkId": "5.1",
          "type": "choice",
          "text": "What is the highest level of education achieved?",
          "prefix": "5.",
          "extension": [
            {
              "url": "http://hl7.org/fhir/StructureDefinition/questionnaire-itemControl",
              "valueCodeableConcept": {
                "coding": [
                  {
                    "system": "http://hl7.org/fhir/questionnaire-item-control",
                    "code": "radio-button",
                    "display": "Radio Button"
                  }
                ],
                "text": "Radio button"
              }
            }
          ],
          "answerOption": [
            {
              "valueCoding": {
                "code": "education",
                "display": "Does not know level of education"
              }
            },
            {
              "valueCoding": {
                "code": "primary-school",
                "display": "Primary school"
              }
            },
            {
              "valueCoding": {
                "code": "secondary-school",
                "display": "Secondary school"
              }
            },
            {
              "valueCoding": {
                "code": "higher-education",
                "display": "Higher education"
              }
            }
          ]
        }
      ]
    },
    {
      "linkId": "6",
      "type": "group",
      "extension": [
        {
          "url": "http://hl7.org/fhir/StructureDefinition/questionnaire-itemControl",
          "valueCodeableConcept": {
            "coding": [
              {
                "system": "http://hl7.org/fhir/questionnaire-item-control",
                "code": "page",
                "display": "Page"
              }
            ],
            "text": "Page"
          }
        }
      ],
      "item": [
        {
          "linkId": "6.1",
          "type": "choice",
          "repeats": true,
          "text": "Who does the client live with?",
          "prefix": "6.",
          "extension": [
            {
              "url": "http://hl7.org/fhir/StructureDefinition/questionnaire-itemControl",
              "valueCodeableConcept": {
                "coding": [
                  {
                    "system": "http://hl7.org/fhir/questionnaire-item-control",
                    "code": "check-box",
                    "display": "Checkbox"
                  }
                ],
                "text": "Checkbox"
              }
            }
          ],
          "answerOption": [
            {
              "valueCoding": {
                "code": "Parents",
                "display": "Parents"
              }
            },
            {
              "valueCoding": {
                "code": "siblings",
                "display": "Siblings"
              }
            },
            {
              "valueCoding": {
                "code": "extended-family",
                "display": "Extended family"
              }
            },
            {
              "valueCoding": {
                "code": "partner",
                "display": "Partner"
              }
            },
            {
              "valueCoding": {
                "code": "friends",
                "display": "Friend(s)"
              }
            },
            {
              "valueCoding": {
                "code": "no-one",
                "display": "No one"
              }
            }
          ]
        }
      ]
    },
    {
      "linkId": "7",
      "type": "group",
      "extension": [
        {
          "url": "http://hl7.org/fhir/StructureDefinition/questionnaire-itemControl",
          "valueCodeableConcept": {
            "coding": [
              {
                "system": "http://hl7.org/fhir/questionnaire-item-control",
                "code": "page",
                "display": "Page"
              }
            ],
            "text": "Page"
          }
        }
      ],
      "item": [
        {
          "linkId": "7.1",
          "type": "choice",
          "text": "Has the client received this year’s seasonal flu vaccine?",
          "prefix": "7.",
          "extension": [
            {
              "url": "http://hl7.org/fhir/StructureDefinition/questionnaire-itemControl",
              "valueCodeableConcept": {
                "coding": [
                  {
                    "system": "http://hl7.org/fhir/questionnaire-item-control",
                    "code": "radio-button",
                    "display": "Radio Button"
                  }
                ],
                "text": "Radio button"
              }
            }
          ],
          "answerOption": [
            {
              "valueCoding": {
                "code": "yes",
                "display": "Yes"
              }
            },
            {
              "valueCoding": {
                "code": "no",
                "display": "No"
              }
            },
            {
              "valueCoding": {
                "code": "unknown",
                "display": "Unknown"
              }
            }
          ]
        }
      ]
    },
    {
      "linkId": "8",
      "type": "group",
      "extension": [
        {
          "url": "http://hl7.org/fhir/StructureDefinition/questionnaire-itemControl",
          "valueCodeableConcept": {
            "coding": [
              {
                "system": "http://hl7.org/fhir/questionnaire-item-control",
                "code": "page",
                "display": "Page"
              }
            ],
            "text": "Page"
          }
        }
      ],
      "item": [
        {
          "linkId": "8.1",
          "type": "date",
          "text": "When was their last menstrual period? (LMP)",
          "prefix": "8."
        }
      ]
    },
    {
      "linkId": "9",
      "type": "group",
      "extension": [
        {
          "url": "http://hl7.org/fhir/StructureDefinition/questionnaire-itemControl",
          "valueCodeableConcept": {
            "coding": [
              {
                "system": "http://hl7.org/fhir/questionnaire-item-control",
                "code": "page",
                "display": "Page"
              }
            ],
            "text": "Page"
          }
        }
      ],
      "item": [
        {
          "linkId": "9.1",
          "type": "integer",
          "text": "How many times have they been pregnant?",
          "prefix": "9.",
          "extension": [
            {
              "url": "http://hl7.org/fhir/StructureDefinition/questionnaire-itemControl",
              "valueCodeableConcept": {
                "coding": [
                  {
                    "system": "http://hl7.org/fhir/questionnaire-item-control",
                    "code": "slider",
                    "display": "Slider"
                  }
                ],
                "text": "Slider"
              }
            }
          ]
        }
      ]
    },
    {
      "linkId": "10",
      "type": "group",
      "extension": [
        {
          "url": "http://hl7.org/fhir/StructureDefinition/questionnaire-itemControl",
          "valueCodeableConcept": {
            "coding": [
              {
                "system": "http://hl7.org/fhir/questionnaire-item-control",
                "code": "page",
                "display": "Page"
              }
            ],
            "text": "Page"
          }
        }
      ],
      "item": [
        {
          "linkId": "10.1",
          "type": "dateTime",
          "text": "What was the date and time of the ultrasound?",
          "prefix": "10."
        }
      ]
    }
  ]
}
